petstoremodels/__init__.py
petstoremodels/device.py
petstoremodels/pet.py
petstoremodels/user.py
petstoremodels-0.0.4.dist-info/METADATA
petstoremodels-0.0.4.dist-info/WHEEL
petstoremodels-0.0.4.dist-info/top_level.txt
petstoremodels-0.0.4.dist-info/RECORD
