Metadata-Version: 2.1
Name: petstoremodels
Version: 0.0.4
Summary: Pydantic models for the petstore microservice.
Author: PandasAreBears
Keywords: models,petstore,pydantic
Requires-Python: >=3.5
Requires-Dist: pydantic
